<annotation>
	<folder>images</folder>
	<filename>fr1653.jpg</filename>
	<path>/Users/sivakumarswaminathan/Desktop/Scross/images/fr1653.jpg</path>
	<source>
		<database>Unknown</database>
	</source>
	<size>
		<width>1920</width>
		<height>1080</height>
		<depth>3</depth>
	</size>
	<segmented>0</segmented>
	<object>
		<name>shvs</name>
		<pose>Unspecified</pose>
		<truncated>0</truncated>
		<difficult>0</difficult>
		<bndbox>
			<xmin>1094</xmin>
			<ymin>608</ymin>
			<xmax>1400</xmax>
			<ymax>755</ymax>
		</bndbox>
	</object>
</annotation>
